distpipe/__init__.py
distpipe/distpipe.py
distpipe/message.py
distpipe/transport.py
distpipe-0.0.1.dist-info/licenses/LICENSE
distpipe-0.0.1.dist-info/METADATA
distpipe-0.0.1.dist-info/WHEEL
distpipe-0.0.1.dist-info/top_level.txt
distpipe-0.0.1.dist-info/RECORD
