Metadata-Version: 2.4
Name: distpipe
Version: 0.0.1
Summary: DistPipe is a distributed framework to implement device-cloud collaborative workflow.
Home-page: https://github.com/ThomasAtlantis/DistPipe
Author: Shangyu Liu
Author-email: liushangyu@sjtu.edu.cn
Classifier: Programming Language :: Python :: 3
Classifier: License :: OSI Approved :: MIT License
Classifier: Operating System :: OS Independent
Requires-Python: >=3.7
License-File: LICENSE
Dynamic: author
Dynamic: author-email
Dynamic: classifier
Dynamic: description
Dynamic: description-content-type
Dynamic: home-page
Dynamic: license-file
Dynamic: requires-python
Dynamic: summary
